unique_audit/__init__.py
unique_audit/admin.py
unique_audit/admin_helpers.py
unique_audit/apps.py
unique_audit/backends.py
unique_audit/local_settings.py
unique_audit/models.py
unique_audit/settings.py
unique_audit/utils.py
unique_audit/views.py
unique_audit/middleware/__init__.py
unique_audit/middleware/unique_audit.py
unique_audit/migrations/0001_initial.py
unique_audit/migrations/__init__.py
unique_audit/signals/__init__.py
unique_audit/signals/auth_signals.py
unique_audit/signals/model_signals.py
unique_audit/signals/request_signals.py
unique_audit/templates/admin/unique_audit/change_list.html
unique_audit/templates/admin/unique_audit/purge_confirmation.html
django_unique_audit-0.0.1.dist-info/LICENSE
django_unique_audit-0.0.1.dist-info/METADATA
django_unique_audit-0.0.1.dist-info/WHEEL
django_unique_audit-0.0.1.dist-info/top_level.txt
django_unique_audit-0.0.1.dist-info/RECORD
