Metadata-Version: 2.1
Name: django-unique-audit
Version: 0.0.1
Summary: An app that creates a unique django audit log across multiple instances.
Home-page: https://github.com/yeongbin-jo/django-unique-audit
Author: Yeongbin Jo
Author-email: iam.yeongbin.jo@gmail.com
License: GPL3
Platform: UNKNOWN
Classifier: Environment :: Plugins
Classifier: Framework :: Django
Classifier: Framework :: Django :: 2.2
Classifier: Framework :: Django :: 3.0
Classifier: Framework :: Django :: 3.1
Classifier: Framework :: Django :: 3.2
Classifier: Framework :: Django :: 4.0
Classifier: Intended Audience :: Developers
Classifier: License :: OSI Approved :: GNU General Public License v3 (GPLv3)
Classifier: Operating System :: OS Independent
Classifier: Programming Language :: Python :: 3
Classifier: Programming Language :: Python :: 3 :: Only
Classifier: Programming Language :: Python :: 3.5
Classifier: Programming Language :: Python :: 3.6
Classifier: Programming Language :: Python :: 3.7
Classifier: Programming Language :: Python :: 3.8
Classifier: Programming Language :: Python :: 3.9
Classifier: Programming Language :: Python :: 3.10
Classifier: Topic :: Software Development :: Libraries :: Python Modules
Requires-Python: >=3.5
License-File: LICENSE
Requires-Dist: beautifulsoup4
Requires-Dist: django (<=4,>=2.2)
